zlogger.py
zlogger-0.1.3.dist-info/METADATA
zlogger-0.1.3.dist-info/WHEEL
zlogger-0.1.3.dist-info/top_level.txt
zlogger-0.1.3.dist-info/RECORD
