Metadata-Version: 2.1
Name: zlogger
Version: 0.1.3
Summary: 对logging进行二次封装, 操作更简单
Home-page: https://gitea.zlyuan.pub/zlyuancn/zlogger
Author: zlyuan
Author-email: zlyuancn@163.com
License: GNU GENERAL PUBLIC LICENSE
Platform: all
Classifier: Programming Language :: Python :: 3
